{
  "_app": {
    "blake3": "65903091ffc4ce88b843bfe5262b61dd4cf65e35cd4d5b6a05aa3f7916a8b522",
    "file_size": 5190414,
    "retrieved": "2026-03-22",
    "sha256": "2f09bb6b3b7a61094d52ba2d7dff40c1ca74a625e0ae0379b960e4d71d4c8718",
    "spot_hash": "dca90715e9e7b07c6b3364db87b6fb948d77264238a9c19c6169ecd91acd8915"
  },
  "attribution": "Dimitris Christopoulos, XC1002565. Accessible at www.xeno-canto.org/1002565",
  "cnt": "Swaziland",
  "date": "2025-05-17",
  "en": "Banana Serotine",
  "file_url": "https://xeno-canto.org/1002565/download",
  "gen": "Afronycteris",
  "lat": "-26.465",
  "length": "0:05",
  "lic": "//creativecommons.org/licenses/by-nc-sa/4.0/",
  "loc": "Siteki, Lubombo Region",
  "lon": "31.945",
  "q": "B",
  "rec": "Dimitris Christopoulos",
  "smp": 500000,
  "source": "xeno-canto",
  "sp": "nanus",
  "time": "09:20",
  "type": "echolocation",
  "url": "https://www.xeno-canto.org/1002565",
  "xc_id": 1002565
}
