{
  "_app": {
    "blake3": "3f8ef687b43caaa290a686547cbd4c00d956bf2d43f2e084cf764a82e83ba073",
    "file_size": 15118094,
    "retrieved": "2026-03-22",
    "sha256": "b7dea60e435a024201f75205eb0ed5b0761dcd557a9fcd1b900d881543bc8581",
    "spot_hash": "6e006d7e3afccffad765ad191a093f9bde4d3caa04c7926bb6e4f7cc309e1f3d"
  },
  "attribution": "Dimitris Christopoulos, XC1002581. Accessible at www.xeno-canto.org/1002581",
  "cnt": "Swaziland",
  "date": "2025-05-17",
  "en": "Dusky Pipistrelle",
  "file_url": "https://xeno-canto.org/1002581/download",
  "gen": "Pipistrellus",
  "lat": "-26.465",
  "length": "0:15",
  "lic": "//creativecommons.org/licenses/by-nc-sa/4.0/",
  "loc": "Siteki, Lubombo Region",
  "lon": "31.945",
  "q": "B",
  "rec": "Dimitris Christopoulos",
  "smp": 500000,
  "source": "xeno-canto",
  "sp": "hesperidus",
  "time": "10:17",
  "type": "echolocation",
  "url": "https://www.xeno-canto.org/1002581",
  "xc_id": 1002581
}
