{
  "_app": {
    "blake3": "88df305f9dd1b8c8452b112f85cb1e35c162f7772f593e2c6dfc7b9815481066",
    "content_hash": "46986447330cf3e45276a0c3e61e0abde459fd90c89ac0ed2fe69df626d3e09c",
    "data_offset": 44,
    "data_size": 5696000,
    "file_size": 5696260,
    "retrieved": "2026-03-22",
    "sha256": "c4224f03a992fe5e5cd58f5b772a255e2558694284ceffa9c370584cbf622128",
    "spot_hash_b3": "948989d8e9fd45f34bbc7873af1ba1b12fef4fbd5ffc9a20badf522bbca18f75"
  },
  "also": [],
  "alt": "600",
  "animal-seen": "no",
  "attribution": "Joaquín Ugarte-Núñez, XC822005. Accessible at www.xeno-canto.org/822005",
  "auto": "yes",
  "cnt": "Peru",
  "date": "2018-07-10",
  "dvc": "EchoMeter Touch 2.0",
  "en": "Blunt-eared Bat",
  "file": "https://xeno-canto.org/822005/download",
  "file-name": "XC822005-No_ID_20180710_202008.wav",
  "gen": "Tomopeas",
  "grp": "bats",
  "lat": "-14.8265",
  "length": "0:11",
  "lic": "https://creativecommons.org/licenses/by-nc-sa/4.0/",
  "loc": "Nazca, Nazca Province, Ica",
  "lon": "-74.9326",
  "method": "field recording",
  "mic": "Internal",
  "playback-used": "no",
  "q": "B",
  "rec": "Joaquín Ugarte-Núñez",
  "regnr": "MP000000004",
  "retrieved": "2026-04-15",
  "rmk": "The recording is not modified.\r\nCoastal city with some agricultural landscape surround. \r\nEcholocation in search phase.",
  "sex": "uncertain",
  "smp": 256000,
  "source": "xeno-canto",
  "sp": "ravus",
  "ssp": "",
  "stage": "uncertain",
  "temp": "",
  "time": "20:30",
  "type": "echolocation",
  "uploaded": "2023-08-12",
  "url": "https://xeno-canto.org/822005",
  "xc_id": 822005
}
